django_simple_analytics-1.2.0.dist-info/licenses/LICENCE
simple_analytics/__init__.py
simple_analytics/admin.py
simple_analytics/apps.py
simple_analytics/middleware.py
simple_analytics/models.py
simple_analytics/migrations/0001_initial.py
simple_analytics/migrations/0002_visitperpage_origin.py
simple_analytics/migrations/0003_visitperpage_user_agent.py
simple_analytics/migrations/__init__.py
django_simple_analytics-1.2.0.dist-info/METADATA
django_simple_analytics-1.2.0.dist-info/WHEEL
django_simple_analytics-1.2.0.dist-info/top_level.txt
django_simple_analytics-1.2.0.dist-info/RECORD
