Metadata-Version: 2.4
Name: django-simple-analytics
Version: 1.2.0
Summary: A simple django packages to track requests on the site
Author-email: Ferran Jovell <ferran.jovell+gh@gmail.com>
Project-URL: homepage, https://github.com/mrswats/django-simple-analytics
Project-URL: Bug Tracker, https://github.com/mrswats/django-simple-analytics/issues
Keywords: django,analytics
Classifier: Intended Audience :: Developers
Classifier: License :: OSI Approved :: MIT License
Classifier: Programming Language :: Python :: 3.9
Classifier: Programming Language :: Python :: 3.10
Classifier: Programming Language :: Python :: 3.11
Classifier: Programming Language :: Python :: 3.12
Classifier: Programming Language :: Python :: 3.13
Classifier: Operating System :: OS Independent
Classifier: Topic :: Software Development :: Libraries
Classifier: Topic :: Utilities
Classifier: Environment :: Web Environment
Classifier: Framework :: Django
Requires-Python: >=3.9
License-File: LICENCE
Requires-Dist: Django>=4.1.0
Provides-Extra: test
Requires-Dist: pytest==7.1.2; extra == "test"
Requires-Dist: pytest-cov==3.0.0; extra == "test"
Requires-Dist: pytest-django==4.5.2; extra == "test"
Requires-Dist: pytest-sugar==0.9.5; extra == "test"
Requires-Dist: time-machine==2.16.0; extra == "test"
Requires-Dist: django-stubs[compatible-mypy]==1.12.0; extra == "test"
Requires-Dist: typing-extensions==4.3.0; extra == "test"
Dynamic: license-file
